MANIFEST.in
README.md
requirements.txt
setup.cfg
setup.py
docs/requirements.txt
tests/__init__.py
tests/requirements.txt
tests/test_twinpics.py
twinpics/__init__.py
twinpics/api.py
twinpics.egg-info/PKG-INFO
twinpics.egg-info/SOURCES.txt
twinpics.egg-info/dependency_links.txt
twinpics.egg-info/requires.txt
twinpics.egg-info/top_level.txt