Metadata-Version: 2.1
Name: twinpics
Version: 0.0.204
Summary: twinpics — Social Media Prediction Model
Home-page: https://www.github.com/albMart/twinpics
Author: Alberto Martín Mateos and Niloufar Shoeibi
Author-email: albmartinmateos@gmail.com
License: MIT License
Download-URL: https://github.com/albMart/twinpics/archive/0.0.1.tar.gz
Project-URL: Bug Reports, https://github.com/albMart/twinpics/issues
Project-URL: Source, https://github.com/albMart/twinpics
Project-URL: Documentation, https://twinpics.readthedocs.io/
Platform: UNKNOWN
Classifier: Development Status :: 4 - Beta
Classifier: Programming Language :: Python :: 3 :: Only
Classifier: Programming Language :: Python :: 3.5
Classifier: Programming Language :: Python :: 3.6
Classifier: Programming Language :: Python :: 3.7
Classifier: Programming Language :: Python :: 3.8
Classifier: License :: OSI Approved :: MIT License
Classifier: Intended Audience :: Developers
Classifier: Topic :: Software Development :: Libraries
Requires-Python: >=3
Provides-Extra: docs
Provides-Extra: tests
